logmagic/MongoHandler.py
logmagic/__init__.py
logmagic/loggerutil.py
logmagic-0.0.1.dist-info/LICENSE
logmagic-0.0.1.dist-info/METADATA
logmagic-0.0.1.dist-info/WHEEL
logmagic-0.0.1.dist-info/top_level.txt
logmagic-0.0.1.dist-info/RECORD
