Metadata-Version: 2.1
Name: logmagic
Version: 0.0.1
Summary: Log helper
Home-page: https://github.com/nitinkatkam/logmagic
Author: Katkam Nitin Narsing Reddy
Author-email: redknitin@gmail.com
License: UNKNOWN
Platform: UNKNOWN
Classifier: Programming Language :: Python :: 3
Classifier: License :: OSI Approved :: MIT License
Classifier: Operating System :: OS Independent
Requires-Python: >=3.6
